{"frameRate":60,"isGlobal":0,"armature":[{"skin":[{"name":"","slot":[{"display":[{"path":"87","type":"image","name":"87","transform":{"skX":90,"skY":90,"x":383.01435}}],"name":"87"},{"display":[{"path":"84","type":"image","name":"84","transform":{"skX":90,"skY":90,"x":385.25915}}],"name":"84"},{"display":[{"path":"78","type":"image","name":"78","transform":{"skX":90,"skY":90,"x":358.93955}}],"name":"78"},{"display":[{"path":"81","type":"image","name":"81","transform":{"skX":90,"skY":90,"x":369.6754}}],"name":"81"},{"display":[{"path":"75","type":"image","name":"75","transform":{"skX":90,"skY":90,"x":351.53055}}],"name":"75"},{"display":[{"path":"88","type":"image","name":"88","transform":{"skX":82.9958,"y":-6.00415,"skY":82.9958,"x":15.67295}}],"name":"88"},{"display":[{"path":"85","type":"image","name":"85","transform":{"skX":75.8277,"y":4.33975,"skY":75.8277,"x":15.1658}}],"name":"85"},{"display":[{"path":"82","type":"image","name":"82","transform":{"skX":108.4349,"y":-10.0007,"skY":108.4349,"x":10.47505}}],"name":"82"},{"display":[{"path":"76","type":"image","name":"76","transform":{"skX":122.4839,"y":0.5015,"skY":122.4839,"x":16.3872}}],"name":"76"},{"display":[{"path":"79","type":"image","name":"79","transform":{"skX":68.1922,"y":-8.70155,"skY":68.1922,"x":15.15175}}],"name":"79"},{"display":[{"path":"91","type":"image","name":"91","transform":{"skX":88.0057,"y":-0.50045,"skY":88.0057,"x":20.11975}}],"name":"91"},{"display":[{"path":"90","type":"image","name":"90","transform":{"skX":90,"skY":90,"x":389.2721}}],"name":"90"}]}],"ik":[],"type":"Armature","name":"Armature","defaultActions":[{"gotoAndPlay":"n8"}],"animation":[{"ik":[],"frame":[],"playTimes":0,"ffd":[],"duration":60,"slot":[{"frame":[{"tweenEasing":null,"displayIndex":-1,"duration":45},{"tweenEasing":null,"duration":15}],"name":"76"},{"frame":[{"tweenEasing":null,"duration":60}],"name":"75"},{"frame":[{"tweenEasing":null,"displayIndex":-1,"duration":60}],"name":"79"},{"frame":[{"tweenEasing":null,"displayIndex":-1,"duration":60}],"name":"78"},{"frame":[{"tweenEasing":null,"displayIndex":-1,"duration":60}],"name":"85"},{"frame":[{"tweenEasing":null,"displayIndex":-1,"duration":60}],"name":"84"},{"frame":[{"tweenEasing":null,"displayIndex":-1,"duration":60}],"name":"91"},{"frame":[{"tweenEasing":null,"displayIndex":-1,"duration":60}],"name":"90"},{"frame":[{"tweenEasing":null,"displayIndex":-1,"duration":60}],"name":"88"},{"frame":[{"tweenEasing":null,"displayIndex":-1,"duration":60}],"name":"87"},{"frame":[{"tweenEasing":null,"displayIndex":-1,"duration":60}],"name":"82"},{"frame":[{"tweenEasing":null,"displayIndex":-1,"duration":60}],"name":"81"}],"bone":[{"frame":[{"transform":{},"duration":60}],"name":"root"},{"frame":[{"tweenEasing":0,"transform":{},"duration":30},{"tweenEasing":0,"transform":{"scX":0.98},"duration":30},{"transform":{},"duration":0}],"name":"bone7"},{"frame":[{"transform":{},"duration":60}],"name":"76"},{"frame":[{"transform":{},"duration":60}],"name":"bone8"},{"frame":[{"transform":{},"duration":60}],"name":"79"},{"frame":[{"transform":{},"duration":60}],"name":"bone10"},{"frame":[{"transform":{},"duration":60}],"name":"85"},{"frame":[{"transform":{},"duration":60}],"name":"bone12"},{"frame":[{"transform":{},"duration":60}],"name":"91"},{"frame":[{"transform":{},"duration":60}],"name":"bone11"},{"frame":[{"transform":{},"duration":60}],"name":"88"},{"frame":[{"transform":{},"duration":60}],"name":"bone9"},{"frame":[{"transform":{},"duration":60}],"name":"82"}],"name":"n8"},{"ik":[],"frame":[],"playTimes":0,"ffd":[],"duration":60,"slot":[{"frame":[{"tweenEasing":null,"displayIndex":-1,"duration":60}],"name":"76"},{"frame":[{"tweenEasing":null,"displayIndex":-1,"duration":60}],"name":"75"},{"frame":[{"tweenEasing":null,"displayIndex":-1,"duration":45},{"tweenEasing":null,"duration":15}],"name":"79"},{"frame":[{"tweenEasing":null,"duration":60}],"name":"78"},{"frame":[{"tweenEasing":null,"displayIndex":-1,"duration":60}],"name":"85"},{"frame":[{"tweenEasing":null,"displayIndex":-1,"duration":60}],"name":"84"},{"frame":[{"tweenEasing":null,"displayIndex":-1,"duration":60}],"name":"91"},{"frame":[{"tweenEasing":null,"displayIndex":-1,"duration":60}],"name":"90"},{"frame":[{"tweenEasing":null,"displayIndex":-1,"duration":60}],"name":"88"},{"frame":[{"tweenEasing":null,"displayIndex":-1,"duration":60}],"name":"87"},{"frame":[{"tweenEasing":null,"displayIndex":-1,"duration":60}],"name":"82"},{"frame":[{"tweenEasing":null,"displayIndex":-1,"duration":60}],"name":"81"}],"bone":[{"frame":[{"transform":{},"duration":60}],"name":"root"},{"frame":[{"transform":{},"duration":60}],"name":"bone7"},{"frame":[{"transform":{},"duration":60}],"name":"76"},{"frame":[{"tweenEasing":0,"transform":{},"duration":30},{"tweenEasing":0,"transform":{"scX":0.98},"duration":30},{"transform":{},"duration":0}],"name":"bone8"},{"frame":[{"transform":{},"duration":60}],"name":"79"},{"frame":[{"transform":{},"duration":60}],"name":"bone10"},{"frame":[{"transform":{},"duration":60}],"name":"85"},{"frame":[{"transform":{},"duration":60}],"name":"bone12"},{"frame":[{"transform":{},"duration":60}],"name":"91"},{"frame":[{"transform":{},"duration":60}],"name":"bone11"},{"frame":[{"transform":{},"duration":60}],"name":"88"},{"frame":[{"transform":{},"duration":60}],"name":"bone9"},{"frame":[{"transform":{},"duration":60}],"name":"82"}],"name":"n9"},{"ik":[],"frame":[],"playTimes":0,"ffd":[],"duration":60,"slot":[{"frame":[{"tweenEasing":null,"displayIndex":-1,"duration":60}],"name":"76"},{"frame":[{"tweenEasing":null,"displayIndex":-1,"duration":60}],"name":"75"},{"frame":[{"tweenEasing":null,"displayIndex":-1,"duration":60}],"name":"79"},{"frame":[{"tweenEasing":null,"displayIndex":-1,"duration":60}],"name":"78"},{"frame":[{"tweenEasing":null,"displayIndex":-1,"duration":60}],"name":"85"},{"frame":[{"tweenEasing":null,"displayIndex":-1,"duration":60}],"name":"84"},{"frame":[{"tweenEasing":null,"displayIndex":-1,"duration":60}],"name":"91"},{"frame":[{"tweenEasing":null,"displayIndex":-1,"duration":60}],"name":"90"},{"frame":[{"tweenEasing":null,"displayIndex":-1,"duration":60}],"name":"88"},{"frame":[{"tweenEasing":null,"displayIndex":-1,"duration":60}],"name":"87"},{"frame":[{"tweenEasing":null,"displayIndex":-1,"duration":45},{"tweenEasing":null,"duration":15}],"name":"82"},{"frame":[{"tweenEasing":null,"duration":60}],"name":"81"}],"bone":[{"frame":[{"transform":{},"duration":60}],"name":"root"},{"frame":[{"transform":{},"duration":60}],"name":"bone7"},{"frame":[{"transform":{},"duration":60}],"name":"76"},{"frame":[{"transform":{},"duration":60}],"name":"bone8"},{"frame":[{"transform":{},"duration":60}],"name":"79"},{"frame":[{"transform":{},"duration":60}],"name":"bone10"},{"frame":[{"transform":{},"duration":60}],"name":"85"},{"frame":[{"transform":{},"duration":60}],"name":"bone12"},{"frame":[{"transform":{},"duration":60}],"name":"91"},{"frame":[{"transform":{},"duration":60}],"name":"bone11"},{"frame":[{"transform":{},"duration":60}],"name":"88"},{"frame":[{"tweenEasing":0,"transform":{},"duration":30},{"tweenEasing":0,"transform":{"scX":0.98},"duration":30},{"transform":{},"duration":0}],"name":"bone9"},{"frame":[{"transform":{},"duration":60}],"name":"82"}],"name":"n10"},{"ik":[],"frame":[],"playTimes":0,"ffd":[],"duration":60,"slot":[{"frame":[{"tweenEasing":null,"displayIndex":-1,"duration":60}],"name":"76"},{"frame":[{"tweenEasing":null,"displayIndex":-1,"duration":60}],"name":"75"},{"frame":[{"tweenEasing":null,"displayIndex":-1,"duration":60}],"name":"79"},{"frame":[{"tweenEasing":null,"displayIndex":-1,"duration":60}],"name":"78"},{"frame":[{"tweenEasing":null,"displayIndex":-1,"duration":45},{"tweenEasing":null,"duration":15}],"name":"85"},{"frame":[{"tweenEasing":null,"duration":60}],"name":"84"},{"frame":[{"tweenEasing":null,"displayIndex":-1,"duration":60}],"name":"91"},{"frame":[{"tweenEasing":null,"displayIndex":-1,"duration":60}],"name":"90"},{"frame":[{"tweenEasing":null,"displayIndex":-1,"duration":60}],"name":"88"},{"frame":[{"tweenEasing":null,"displayIndex":-1,"duration":60}],"name":"87"},{"frame":[{"tweenEasing":null,"displayIndex":-1,"duration":60}],"name":"82"},{"frame":[{"tweenEasing":null,"displayIndex":-1,"duration":60}],"name":"81"}],"bone":[{"frame":[{"transform":{},"duration":60}],"name":"root"},{"frame":[{"transform":{},"duration":60}],"name":"bone7"},{"frame":[{"transform":{},"duration":60}],"name":"76"},{"frame":[{"transform":{},"duration":60}],"name":"bone8"},{"frame":[{"transform":{},"duration":60}],"name":"79"},{"frame":[{"tweenEasing":0,"transform":{},"duration":30},{"tweenEasing":0,"transform":{"scX":0.98},"duration":30},{"transform":{},"duration":0}],"name":"bone10"},{"frame":[{"transform":{},"duration":60}],"name":"85"},{"frame":[{"transform":{},"duration":60}],"name":"bone12"},{"frame":[{"transform":{},"duration":60}],"name":"91"},{"frame":[{"transform":{},"duration":60}],"name":"bone11"},{"frame":[{"transform":{},"duration":60}],"name":"88"},{"frame":[{"transform":{},"duration":60}],"name":"bone9"},{"frame":[{"transform":{},"duration":60}],"name":"82"}],"name":"n11"},{"ik":[],"frame":[],"playTimes":0,"ffd":[],"duration":60,"slot":[{"frame":[{"tweenEasing":null,"displayIndex":-1,"duration":60}],"name":"76"},{"frame":[{"tweenEasing":null,"displayIndex":-1,"duration":60}],"name":"75"},{"frame":[{"tweenEasing":null,"displayIndex":-1,"duration":60}],"name":"79"},{"frame":[{"tweenEasing":null,"displayIndex":-1,"duration":60}],"name":"78"},{"frame":[{"tweenEasing":null,"displayIndex":-1,"duration":60}],"name":"85"},{"frame":[{"tweenEasing":null,"displayIndex":-1,"duration":60}],"name":"84"},{"frame":[{"tweenEasing":null,"displayIndex":-1,"duration":60}],"name":"91"},{"frame":[{"tweenEasing":null,"displayIndex":-1,"duration":60}],"name":"90"},{"frame":[{"tweenEasing":null,"displayIndex":-1,"duration":45},{"tweenEasing":null,"duration":15}],"name":"88"},{"frame":[{"tweenEasing":null,"duration":60}],"name":"87"},{"frame":[{"tweenEasing":null,"displayIndex":-1,"duration":60}],"name":"82"},{"frame":[{"tweenEasing":null,"displayIndex":-1,"duration":60}],"name":"81"}],"bone":[{"frame":[{"transform":{},"duration":60}],"name":"root"},{"frame":[{"transform":{},"duration":60}],"name":"bone7"},{"frame":[{"transform":{},"duration":60}],"name":"76"},{"frame":[{"transform":{},"duration":60}],"name":"bone8"},{"frame":[{"transform":{},"duration":60}],"name":"79"},{"frame":[{"transform":{},"duration":60}],"name":"bone10"},{"frame":[{"transform":{},"duration":60}],"name":"85"},{"frame":[{"transform":{},"duration":60}],"name":"bone12"},{"frame":[{"transform":{},"duration":60}],"name":"91"},{"frame":[{"tweenEasing":0,"transform":{},"duration":30},{"tweenEasing":0,"transform":{"scX":0.98},"duration":30},{"transform":{},"duration":0}],"name":"bone11"},{"frame":[{"transform":{},"duration":60}],"name":"88"},{"frame":[{"transform":{},"duration":60}],"name":"bone9"},{"frame":[{"transform":{},"duration":60}],"name":"82"}],"name":"n12"},{"ik":[],"frame":[],"playTimes":0,"ffd":[],"duration":60,"slot":[{"frame":[{"tweenEasing":null,"displayIndex":-1,"duration":60}],"name":"76"},{"frame":[{"tweenEasing":null,"displayIndex":-1,"duration":60}],"name":"75"},{"frame":[{"tweenEasing":null,"displayIndex":-1,"duration":60}],"name":"79"},{"frame":[{"tweenEasing":null,"displayIndex":-1,"duration":60}],"name":"78"},{"frame":[{"tweenEasing":null,"displayIndex":-1,"duration":60}],"name":"85"},{"frame":[{"tweenEasing":null,"displayIndex":-1,"duration":60}],"name":"84"},{"frame":[{"tweenEasing":null,"displayIndex":-1,"duration":45},{"tweenEasing":null,"duration":15}],"name":"91"},{"frame":[{"tweenEasing":null,"duration":60}],"name":"90"},{"frame":[{"tweenEasing":null,"displayIndex":-1,"duration":60}],"name":"88"},{"frame":[{"tweenEasing":null,"displayIndex":-1,"duration":60}],"name":"87"},{"frame":[{"tweenEasing":null,"displayIndex":-1,"duration":60}],"name":"82"},{"frame":[{"tweenEasing":null,"displayIndex":-1,"duration":60}],"name":"81"}],"bone":[{"frame":[{"transform":{},"duration":60}],"name":"root"},{"frame":[{"transform":{},"duration":60}],"name":"bone7"},{"frame":[{"transform":{},"duration":60}],"name":"76"},{"frame":[{"transform":{},"duration":60}],"name":"bone8"},{"frame":[{"transform":{},"duration":60}],"name":"79"},{"frame":[{"transform":{},"duration":60}],"name":"bone10"},{"frame":[{"transform":{},"duration":60}],"name":"85"},{"frame":[{"tweenEasing":0,"transform":{},"duration":30},{"tweenEasing":0,"transform":{"scX":0.98},"duration":30},{"transform":{},"duration":0}],"name":"bone12"},{"frame":[{"transform":{},"duration":60}],"name":"91"},{"frame":[{"transform":{},"duration":60}],"name":"bone11"},{"frame":[{"transform":{},"duration":60}],"name":"88"},{"frame":[{"transform":{},"duration":60}],"name":"bone9"},{"frame":[{"transform":{},"duration":60}],"name":"82"}],"name":"n13"}],"bone":[{"name":"root","transform":{}},{"length":558,"transform":{"skX":-90,"y":351.53055,"skY":-90},"parent":"root","name":"bone7"},{"length":641,"transform":{"skX":-90,"y":358.93955,"skY":-90},"parent":"root","name":"bone8"},{"length":654,"transform":{"skX":-90,"y":385.25915,"skY":-90},"parent":"root","name":"bone10"},{"length":726.5,"transform":{"skX":-90,"y":389.2721,"skY":-90},"parent":"root","name":"bone12"},{"length":634,"transform":{"skX":-90,"y":383.01435,"skY":-90},"parent":"root","name":"bone11"},{"length":682.5,"transform":{"skX":-90,"y":369.6754,"skY":-90},"parent":"root","name":"bone9"},{"length":33.5,"transform":{"skX":7.0042,"y":0.66595,"skY":7.0042,"x":545.1188},"parent":"bone11","name":"88"},{"length":30.5,"transform":{"skX":14.1723,"y":-32.3397,"skY":14.1723,"x":498.84005},"parent":"bone10","name":"85"},{"length":45.5,"transform":{"skX":1.9943,"y":28.77135,"skY":1.9943,"x":564.8843},"parent":"bone12","name":"91"},{"length":34.5,"transform":{"skX":-32.4839,"y":-53.9684,"skY":-32.4839,"x":562.38295},"parent":"bone7","name":"76"},{"length":41,"transform":{"skX":21.8078,"y":3.9504,"skY":21.8078,"x":528.6867},"parent":"bone8","name":"79"},{"length":28,"transform":{"skX":-18.4349,"y":34.38195,"skY":-18.4349,"x":524.29045},"parent":"bone9","name":"82"}],"aabb":{"width":609.5,"y":-390,"height":780,"x":-304.75},"frameRate":60,"slot":[{"name":"75","parent":"bone7","color":{}},{"z":1,"name":"76","parent":"76","color":{}},{"z":2,"name":"78","parent":"bone8","color":{}},{"z":3,"name":"79","parent":"79","color":{}},{"z":4,"name":"81","parent":"bone9","color":{}},{"z":5,"name":"82","parent":"82","color":{}},{"z":6,"name":"84","parent":"bone10","color":{}},{"z":7,"name":"85","parent":"85","color":{}},{"z":8,"name":"87","parent":"bone11","color":{}},{"z":9,"name":"88","parent":"88","color":{}},{"z":10,"name":"90","parent":"bone12","color":{}},{"z":11,"name":"91","parent":"91","color":{}}]}],"name":"scys3","version":"4.5"}