{"SubTexture":[{"width":249,"y":717,"height":249,"name":"g","x":814},{"frameX":-1,"frameHeight":168,"y":858,"frameY":-1,"frameWidth":254,"width":252,"height":167,"name":"1","x":1065},{"frameX":0,"frameHeight":244,"y":1,"frameY":0,"frameWidth":228,"width":227,"height":243,"name":"2","x":1631},{"frameX":-1,"frameHeight":308,"y":752,"frameY":0,"frameWidth":240,"width":239,"height":306,"name":"3","x":351},{"frameX":-10,"frameHeight":424,"y":1514,"frameY":-1,"frameWidth":226,"width":215,"height":421,"name":"4","x":1},{"frameX":-2,"frameHeight":262,"y":1,"frameY":0,"frameWidth":380,"width":374,"height":262,"name":"5","x":252},{"frameX":-1,"frameHeight":272,"y":407,"frameY":0,"frameWidth":226,"width":219,"height":263,"name":"6","x":1239},{"frameX":-1,"frameHeight":140,"y":717,"frameY":0,"frameWidth":308,"width":306,"height":139,"name":"7","x":1065},{"frameX":0,"frameHeight":326,"y":1668,"frameY":-2,"frameWidth":240,"width":239,"height":324,"name":"8","x":910},{"frameX":-1,"frameHeight":310,"y":407,"frameY":-1,"frameWidth":196,"width":194,"height":308,"name":"9","x":1043},{"frameX":-1,"frameHeight":226,"y":308,"frameY":0,"frameWidth":235,"width":233,"height":225,"name":"10","x":1736},{"frameX":-1,"frameHeight":280,"y":1668,"frameY":-1,"frameWidth":290,"width":288,"height":279,"name":"11","x":620},{"frameX":-10,"frameHeight":305,"y":1668,"frameY":-1,"frameWidth":258,"width":247,"height":303,"name":"12","x":1788},{"frameX":-1,"frameHeight":423,"y":1,"frameY":-2,"frameWidth":256,"width":249,"height":421,"name":"13","x":1},{"frameX":-1,"frameHeight":272,"y":1385,"frameY":0,"frameWidth":245,"width":244,"height":271,"name":"14","x":693},{"frameX":-1,"frameHeight":212,"y":1297,"frameY":0,"frameWidth":168,"width":166,"height":210,"name":"15","x":224},{"frameX":-1,"frameHeight":364,"y":1668,"frameY":-1,"frameWidth":210,"width":209,"height":362,"name":"16","x":1151},{"frameX":0,"frameHeight":304,"y":1,"frameY":-1,"frameWidth":224,"width":224,"height":301,"name":"17","x":1405},{"frameX":-9,"frameHeight":278,"y":613,"frameY":-2,"frameWidth":170,"width":160,"height":275,"name":"18","x":1460},{"frameX":-1,"frameHeight":282,"y":798,"frameY":-1,"frameWidth":350,"width":348,"height":281,"name":"19","x":1},{"frameX":-1,"frameHeight":374,"y":424,"frameY":0,"frameWidth":288,"width":281,"height":372,"name":"20","x":1},{"frameX":-11,"frameHeight":260,"y":265,"frameY":0,"frameWidth":392,"width":377,"height":257,"name":"21","x":284},{"frameX":-1,"frameHeight":256,"y":755,"frameY":-1,"frameWidth":144,"width":141,"height":254,"name":"22","x":1622},{"frameX":0,"frameHeight":369,"y":1297,"frameY":0,"frameWidth":226,"width":225,"height":369,"name":"23","x":466},{"frameX":0,"frameHeight":220,"y":535,"frameY":-1,"frameWidth":235,"width":234,"height":218,"name":"24","x":1736},{"frameX":-7,"frameHeight":351,"y":1514,"frameY":-1,"frameWidth":254,"width":246,"height":350,"name":"25","x":218},{"frameX":-1,"frameHeight":166,"y":240,"frameY":-1,"frameWidth":418,"width":417,"height":165,"name":"26","x":986},{"frameX":-2,"frameHeight":347,"y":1668,"frameY":-1,"frameWidth":226,"width":218,"height":344,"name":"27","x":1568},{"frameX":-1,"frameHeight":215,"y":1081,"frameY":0,"frameWidth":396,"width":394,"height":214,"name":"28","x":224},{"frameX":-1,"frameHeight":172,"y":1027,"frameY":0,"frameWidth":246,"width":244,"height":171,"name":"29","x":1065},{"frameX":0,"frameHeight":206,"y":407,"frameY":-1,"frameWidth":274,"width":274,"height":204,"name":"30","x":1460},{"frameX":0,"frameHeight":206,"y":1,"frameY":-1,"frameWidth":316,"width":315,"height":205,"name":"31","x":1026},{"frameX":-10,"frameHeight":338,"y":752,"frameY":-13,"frameWidth":230,"width":220,"height":324,"name":"32","x":592},{"frameX":0,"frameHeight":200,"y":516,"frameY":-1,"frameWidth":355,"width":353,"height":199,"name":"33","x":688},{"frameX":-1,"frameHeight":432,"y":1081,"frameY":0,"frameWidth":228,"width":221,"height":431,"name":"34","x":1},{"frameX":-17,"frameHeight":181,"y":1866,"frameY":0,"frameWidth":390,"width":372,"height":180,"name":"35","x":218},{"frameX":-1,"frameHeight":370,"y":1668,"frameY":0,"frameWidth":206,"width":204,"height":368,"name":"36","x":1362},{"frameX":-1,"frameHeight":306,"y":1078,"frameY":-1,"frameWidth":234,"width":233,"height":305,"name":"37","x":693},{"frameX":-1,"frameHeight":275,"y":240,"frameY":-1,"frameWidth":322,"width":321,"height":274,"name":"38","x":663},{"frameX":-10,"frameHeight":273,"y":1200,"frameY":-7,"frameWidth":152,"width":140,"height":265,"name":"39","x":1065},{"frameX":-10,"frameHeight":237,"y":1,"frameY":0,"frameWidth":408,"width":396,"height":237,"name":"40","x":628},{"frameX":-2,"frameHeight":307,"y":1,"frameY":-1,"frameWidth":180,"width":172,"height":305,"name":"41","x":1860},{"frameX":-1,"frameHeight":227,"y":524,"frameY":-1,"frameWidth":410,"width":402,"height":226,"name":"42","x":284}],"width":2048,"height":2048,"name":"bg","imagePath":"bg_tex.png"}