{"width":2519,"imagePath":"djw_tex.png","height":2048,"name":"djw","SubTexture":[{"width":251,"y":1,"height":320,"name":"17","x":907},{"width":252,"y":1670,"height":328,"name":"20","x":1563},{"width":253,"y":1670,"height":329,"name":"16","x":1308},{"width":250,"y":1670,"height":321,"name":"19","x":1817},{"width":247,"y":681,"height":310,"name":"18","x":1846},{"width":296,"y":1,"height":340,"name":"30","x":309},{"width":298,"y":685,"height":329,"name":"31","x":558},{"width":296,"y":343,"height":340,"name":"34","x":558},{"width":298,"y":1,"height":329,"name":"33","x":607},{"width":302,"y":332,"height":315,"name":"32","x":856},{"width":169,"y":1,"height":399,"name":"35","x":1843},{"width":169,"y":1,"height":380,"name":"21","x":2014},{"width":270,"y":649,"height":346,"name":"13","x":858},{"width":270,"y":1016,"height":347,"name":"09","x":802},{"width":263,"y":352,"height":327,"name":"11","x":1397},{"width":265,"y":649,"height":330,"name":"10","x":1130},{"width":265,"y":997,"height":330,"name":"12","x":1074},{"width":169,"y":1,"height":371,"name":"14","x":2185},{"width":80,"y":1913,"height":95,"name":"22","x":379},{"width":60,"y":1913,"height":120,"name":"36","x":461},{"width":61,"y":383,"height":142,"name":"15","x":2014},{"width":224,"y":1656,"height":334,"name":"38","x":2069},{"width":222,"y":1597,"height":321,"name":"37","x":2295},{"width":224,"y":993,"height":334,"name":"40","x":2048},{"width":223,"y":681,"height":344,"name":"39","x":1621},{"width":223,"y":1027,"height":344,"name":"41","x":1823},{"width":222,"y":681,"height":381,"name":"42","x":1397},{"width":148,"y":1869,"height":166,"name":"43","x":551},{"width":249,"y":1329,"height":339,"name":"03","x":1308},{"width":251,"y":1365,"height":367,"name":"02","x":802},{"width":248,"y":1,"height":349,"name":"04","x":1160},{"width":251,"y":1365,"height":367,"name":"06","x":1055},{"width":250,"y":1,"height":339,"name":"05","x":1410},{"width":78,"y":1869,"height":114,"name":"08","x":701},{"width":262,"y":1734,"height":300,"name":"23","x":802},{"width":262,"y":1064,"height":300,"name":"27","x":1559},{"width":268,"y":1329,"height":266,"name":"25","x":2097},{"width":267,"y":1373,"height":281,"name":"26","x":1559},{"width":267,"y":1373,"height":281,"name":"24","x":1828},{"width":111,"y":1913,"height":133,"name":"29","x":266},{"width":166,"y":383,"height":383,"name":"07","x":2095},{"width":179,"y":1,"height":408,"name":"28","x":1662},{"width":306,"y":1,"height":625,"name":"45","x":1},{"width":285,"y":628,"height":663,"name":"44","x":1},{"width":249,"y":1226,"height":641,"name":"48","x":551},{"width":283,"y":1293,"height":618,"name":"49","x":266},{"width":263,"y":1293,"height":678,"name":"46","x":1},{"width":268,"y":628,"height":596,"name":"47","x":288}]}