{"imagePath":"vs_tex.png","width":1977,"height":1336,"name":"vs","SubTexture":[{"width":373,"y":378,"height":375,"name":"6","x":982},{"width":721,"y":1,"height":375,"name":"4","x":1},{"width":262,"y":755,"height":440,"name":"8","x":982},{"width":415,"y":764,"height":412,"name":"9","x":1},{"width":318,"y":378,"height":412,"name":"7","x":1357},{"width":195,"y":928,"height":230,"name":"2","x":1780},{"width":284,"y":378,"height":340,"name":"3","x":1677},{"width":500,"y":378,"height":384,"name":"11","x":1},{"width":103,"y":720,"height":121,"name":"1","x":1781},{"width":477,"y":378,"height":392,"name":"12","x":503},{"width":527,"y":1,"height":375,"name":"10","x":1433},{"width":707,"y":1,"height":375,"name":"5","x":724},{"width":532,"y":1064,"height":134,"name":"lm","x":1246},{"width":533,"y":908,"height":134,"name":"ml","x":418},{"width":533,"y":792,"height":134,"name":"qy","x":1246},{"width":532,"y":928,"height":134,"name":"sm","x":1246},{"width":593,"y":1178,"height":156,"name":"bb","x":1},{"width":534,"y":772,"height":134,"name":"zy","x":418}]}