{"frameRate":60,"isGlobal":0,"name":"cd","version":"4.5","armature":[{"defaultActions":[{"gotoAndPlay":"cd"}],"type":"Armature","frameRate":60,"slot":[{"color":{},"name":"2","parent":"bone"}],"skin":[{"slot":[{"display":[{"path":"2","type":"image","name":"2","transform":{"y":-0.5031,"skX":89.8234,"skY":89.8234,"x":0.9985}},{"path":"3","type":"image","name":"3","transform":{"y":-3.0216,"skX":89.8234,"skY":89.8234,"x":6.9907}},{"path":"4","type":"image","name":"4","transform":{"y":-8.5138,"skX":89.8234,"skY":89.8234,"x":4.4738}},{"path":"5","type":"image","name":"5","transform":{"y":-11.0554,"skX":89.8234,"skY":89.8234,"x":17.966}},{"path":"6","type":"image","name":"6","transform":{"y":-15.0431,"skX":89.8234,"skY":89.8234,"x":13.9537}},{"path":"7","type":"image","name":"7","transform":{"y":-18.0508,"skX":89.8234,"skY":89.8234,"x":16.4444}},{"path":"8","type":"image","name":"8","transform":{"y":-19.0677,"skX":89.8234,"skY":89.8234,"x":21.9413}},{"path":"9","type":"image","name":"9","transform":{"y":-21.0138,"skX":89.8234,"skY":89.8234,"x":4.4353}},{"path":"10","type":"image","name":"10","transform":{"y":1.983,"skX":89.8234,"skY":89.8234,"x":5.5061}},{"path":"11","type":"image","name":"11","transform":{"y":4.9846,"skX":89.8234,"skY":89.8234,"x":5.0154}},{"path":"12","type":"image","name":"12","transform":{"y":6.483,"skX":89.8234,"skY":89.8234,"x":5.52}},{"path":"13","type":"image","name":"13","transform":{"y":2.4815,"skX":89.8234,"skY":89.8234,"x":6.0077}},{"path":"14","type":"image","name":"14","transform":{"y":3.5185,"skX":89.8234,"skY":89.8234,"x":-5.9892}},{"path":"15","type":"image","name":"15","transform":{"y":4.5231,"skX":89.8234,"skY":89.8234,"x":-7.4861}},{"path":"16","type":"image","name":"16","transform":{"y":5.5894,"skX":89.8234,"skY":89.8234,"x":-28.9829}},{"path":"17","type":"image","name":"17","transform":{"y":-7.4152,"skX":89.8234,"skY":89.8234,"x":-27.523}},{"path":"18","type":"image","name":"18","transform":{"y":-6.4137,"skX":89.8234,"skY":89.8234,"x":-28.0199}},{"path":"19","type":"image","name":"19","transform":{"y":-6.4198,"skX":89.8234,"skY":89.8234,"x":-26.0199}},{"path":"20","type":"image","name":"20","transform":{"y":51.62,"skX":89.8234,"skY":89.8234,"x":-38.8411}},{"path":"21","type":"image","name":"21","transform":{"y":50.9859,"skX":89.8234,"skY":89.8234,"x":4.6572}}],"name":"2"}],"name":""}],"animation":[{"slot":[{"frame":[{"tweenEasing":null,"duration":5},{"tweenEasing":null,"duration":5,"displayIndex":1},{"tweenEasing":null,"duration":5,"displayIndex":2},{"tweenEasing":null,"duration":5,"displayIndex":3},{"tweenEasing":null,"duration":5,"displayIndex":4},{"tweenEasing":null,"duration":5,"displayIndex":5},{"tweenEasing":null,"duration":5,"displayIndex":6},{"tweenEasing":null,"duration":5,"displayIndex":7},{"tweenEasing":null,"duration":5,"displayIndex":8},{"tweenEasing":null,"duration":5,"displayIndex":9},{"tweenEasing":null,"duration":5,"displayIndex":10},{"tweenEasing":null,"duration":5,"displayIndex":11},{"tweenEasing":null,"duration":5,"displayIndex":12},{"tweenEasing":null,"duration":5,"displayIndex":13},{"tweenEasing":null,"duration":5,"displayIndex":14},{"tweenEasing":null,"duration":5,"displayIndex":15},{"tweenEasing":null,"duration":5,"displayIndex":16},{"tweenEasing":null,"duration":5,"displayIndex":17},{"tweenEasing":null,"duration":5,"displayIndex":18},{"tweenEasing":null,"duration":5,"displayIndex":19},{"tweenEasing":null,"duration":0,"displayIndex":-1}],"name":"2"}],"frame":[],"playTimes":0,"ffd":[],"duration":100,"ik":[],"name":"cd","bone":[{"frame":[{"duration":100,"transform":{}}],"name":"root"},{"frame":[{"duration":100,"transform":{}}],"name":"bone"}]}],"ik":[],"name":"armatureName","bone":[{"transform":{},"name":"root"},{"length":178,"transform":{"skX":-89.8234,"skY":-89.8234},"parent":"root","name":"bone"}],"aabb":{"width":97,"y":-45,"height":88,"x":-49}}]}