{"width":512,"SubTexture":[{"width":87,"y":149,"height":137,"name":"yssy","x":270},{"width":89,"y":1,"height":146,"name":"xt","x":334},{"width":109,"y":293,"height":93,"name":"xt2","x":1},{"width":53,"y":288,"height":157,"name":"ttr","x":256},{"width":87,"y":115,"height":145,"name":"syn","x":1},{"width":135,"y":149,"height":75,"name":"qsh3","x":359},{"width":93,"y":89,"height":136,"name":"qhqbjx","x":175},{"width":59,"y":226,"height":151,"name":"kfwn","x":451},{"width":75,"y":1,"height":137,"name":"kfn","x":425},{"width":172,"y":1,"height":112,"name":"c","x":1},{"width":90,"y":227,"height":130,"name":"51","x":359},{"width":128,"y":359,"height":68,"name":"z","x":112},{"width":157,"y":1,"height":86,"name":"ra","x":175},{"width":133,"y":293,"height":36,"name":"z2","x":112},{"width":165,"y":467,"height":36,"name":"z8","x":1},{"width":133,"y":359,"height":35,"name":"z4","x":311},{"width":164,"y":227,"height":64,"name":"z5","x":90},{"width":135,"y":396,"height":34,"name":"z3","x":311},{"width":164,"y":447,"height":36,"name":"z7","x":168},{"width":165,"y":429,"height":36,"name":"z6","x":1},{"width":166,"y":447,"height":35,"name":"z9","x":334}],"height":512,"name":"9ui","imagePath":"9ui_tex.png"}