{"width":2671,"imagePath":"xsjh_tex.png","height":2048,"name":"xsjh","SubTexture":[{"width":298,"y":1936,"height":62,"name":"脚下阴影","x":414},{"width":289,"y":1,"height":704,"name":"7蓝色1","x":1594},{"width":422,"y":686,"height":703,"name":"7蓝色2","x":436},{"width":294,"y":686,"height":710,"name":"6蓝色2","x":1298},{"width":254,"y":1,"height":703,"name":"6蓝色1","x":2415},{"width":273,"y":707,"height":693,"name":"5绿色1","x":1594},{"width":433,"y":686,"height":694,"name":"5绿色2","x":1},{"width":267,"y":1,"height":692,"name":"4粉色1","x":1885},{"width":373,"y":684,"height":697,"name":"4粉色2","x":860},{"width":326,"y":1,"height":683,"name":"3黄色1","x":1235},{"width":390,"y":1,"height":681,"name":"3黄色2","x":541},{"width":274,"y":695,"height":661,"name":"2红色1","x":2139},{"width":276,"y":1,"height":661,"name":"2红色2","x":933},{"width":411,"y":1382,"height":651,"name":"1白色2","x":1},{"width":249,"y":1,"height":655,"name":"1白色1","x":2154},{"width":538,"y":1,"height":683,"name":"首页角色身体","x":1},{"width":119,"y":1936,"height":110,"name":"火光","x":714},{"width":289,"y":1398,"height":519,"name":"身体","x":1298},{"width":70,"y":1866,"height":158,"name":"木柴3","x":835},{"width":155,"y":1588,"height":52,"name":"木柴2","x":1928},{"width":153,"y":2000,"height":46,"name":"木柴1","x":414},{"width":238,"y":1399,"height":187,"name":"酱板鸭","x":1869},{"y":1358,"frameX":0,"frameHeight":245,"frameY":0,"width":465,"frameWidth":466,"height":245,"name":"狐狸","x":2139},{"width":80,"y":1601,"height":120,"name":"手提示","x":1589},{"width":29,"y":1,"height":215,"name":"fd3","x":1563},{"width":40,"y":1588,"height":178,"name":"fd2","x":2085},{"width":51,"y":1402,"height":151,"name":"fd1","x":1806},{"width":215,"y":1402,"height":197,"name":"首页角色右手","x":1589},{"y":1391,"frameX":-1,"frameHeight":171,"frameY":0,"width":113,"frameWidth":114,"height":156,"name":"头1","x":818},{"y":1549,"frameX":-1,"frameHeight":171,"frameY":0,"width":113,"frameWidth":114,"height":156,"name":"头3","x":818},{"width":112,"y":1707,"height":157,"name":"头2","x":818},{"width":120,"y":1588,"height":122,"name":"手","x":1806},{"y":2000,"frameX":-7,"frameHeight":46,"frameY":-1,"width":48,"frameWidth":55,"height":45,"name":"流汗","x":569},{"width":49,"y":686,"height":49,"name":"呼气","x":1235},{"width":30,"y":2000,"height":42,"name":"眼睛冒火","x":619},{"width":268,"y":707,"height":690,"name":"角色3","x":1869},{"width":363,"y":1383,"height":645,"name":"角色1","x":933},{"width":402,"y":1391,"height":543,"name":"角色2","x":414}]}